{"batches":{"current":null,"current_batch":null,"last_completed":167},"collisions":{"total":3,"unresolved":0},"counts":{"resource_files":4147,"translation_units":72513},"exclusions":{"already_localized":3,"collision_not_selected":20,"directory":2264,"localized":1271,"nested_archive":38,"not_in_translation_reference":1003,"not_jar":1898,"unsupported_resource":577039},"findings":{"codes":{"empty_target":44397,"length_ratio":120,"markup_structure_changed":3948,"message_format_invalid":1,"placeholder_mismatch":9588},"counts":{"blocking":57934,"warning":120}},"generation":{"path":"generated/plugin","present":false,"valid":false},"next_command":"python -m scripts.idea_deu next-batch --limit 100","package":{"path":"dist/idea-deu.zip","present":false,"valid":false},"source":{"build":"253.29346.240","hash":"755b9549eb41ddec86ea111e4aba94b4fd6e39a60b1de7945c92652c70f80026","version":"2025.3.1.1"},"stale_units":{"by_reason":{},"count":0,"records":[]},"statuses":{"linguistically_reviewed":0,"open":44397,"technically_reviewed":28036,"translated":80},"workflow_state":"translate"}
